[
    {
        "title": "Forward",
        "to": "forward"
    },
    {
        "title": "Chapter One",
        "to": "chapter1"
    },
    {
        "title": "Chapter Two",
        "to": "chapter2"
    },
    {
        "title": "Chapter Three",
        "to": "chapter3"
    },
    {
        "title": "Chapter Four",
        "to": "chapter4"
    },
    {
        "title": "Chapter Five",
        "to": "chapter5"
    },
    {
        "title": "Chapter Six",
        "to": "chapter6"
    },
    {
        "title": "Chapter Seven",
        "to": "chapter7"
    },
    {
        "title": "Chapter Eight",
        "to": "chapter8"
    },
    {
        "title": "Chapter Nine",
        "to": "chapter9"
    },
    {
        "title": "Chapter Ten",
        "to": "chapter10"
    },
    {
        "title": "Chapter Eleven",
        "to": "chapter11"
    },
    {
        "title": "Chapter Twelve",
        "to": "chapter12"
    }
]